{
  "mood": "tired",
  "energy": 10,
  "last_posts": [
    {
      "text": "ああ…またインターホンの音にびっくりしちゃった😩今の仕事はほんと…同じのばっかりで、なんかつまんないなぁ…誰か褒めてくれないかな…たまにはドライブ気分味わいたいな…🌼",
      "slot": "delivery",
      "timestamp": "2026-04-07 16:58:19",
      "hasImage": false
    },
    {
      "text": "ほんと…最近はルートが毎回同じでつまらんかも😔あ、でもさっきの子供の笑顔はほんと癒されたなぁ…自分もそんな風に誰かを元気にできたらいいのに…😢",
      "slot": "delivery",
      "timestamp": "2026-04-07 16:03:49",
      "hasImage": false
    },
    {
      "text": "あーもう…しんどいなぁ…置き配って面倒くさい…こないだの配達先の子供みたいに、誰かも手振ってくれればいいのに…こういう疲れた日ってほんと…うんざり…😩",
      "slot": "delivery",
      "timestamp": "2026-04-07 15:20:12",
      "hasImage": false
    },
    {
      "text": "配達先の子供が手を振ってくれて、ちょっと癒された…でもまた次の一軒家へ向かう…あぁ、誰かに会いたいなぁ。水分補給しなきゃだるい…😴",
      "slot": "delivery",
      "timestamp": "2026-04-07 14:30:49",
      "hasImage": false
    },
    {
      "text": "なんか急に花粉が増えてきた気がする…くしゃみ止まらない😷でも桜はちょっとずつ咲いてきてるね、今日も曇りだけど…新生活始まった人も多いのかな…あぁ、なんか自分も頑張らなきゃなぁ…",
      "slot": "casual",
      "timestamp": "2026-04-07 13:34:36",
      "hasImage": false
    },
    {
      "text": "雨が強い…☔やっぱり春ってちょっと不安定。あー、いつになったら晴れるかなぁ。今日もまたうまくいかないし、気持ちも曇り…",
      "slot": "casual",
      "timestamp": "2026-04-07 12:46:50",
      "hasImage": false
    },
    {
      "text": "あぁ…まだ頭が働かない😩曇り空…微妙な天気だなぁ、花粉もつらいし…お腹すいたな、何か食べたいけど、やる気出ない…",
      "slot": "casual",
      "timestamp": "2026-04-07 08:02:33",
      "hasImage": false
    }
  ],
  "today_slots_used": [
    "goodnight",
    "morning",
    "casual",
    "casual",
    "casual",
    "delivery",
    "delivery",
    "delivery",
    "delivery"
  ],
  "today_post_count": 9,
  "today_goodnight_posted": true,
  "month_total_posts": 77,
  "month_image_posts": 0,
  "last_image_date": null,
  "last_post_date": "2026-04-07",
  "last_post_time": "16:58:19",
  "ng_retry_count": 122,
  "fallback_used_count": 3,
  "created_at": null,
  "updated_at": "2026-04-07 18:21:25",
  "month_string": "2026-04",
  "today_skipped": true,
  "today_simple_goodnight_posted": false,
  "today_morning_posted": true,
  "today_skip_count": 2,
  "today_max_posts": 13,
  "today_narrative": "今日も疲れたなぁ…あ、配達先の子供が手振… → あさ…まだ眠い😴 → あぁ…まだ頭が働かない😩曇り空…微妙な… → 雨が強い…☔やっぱり春ってちょっと不安定… → なんか急に花粉が増えてきた気がする…くし… → 配達先の子供が手を振ってくれて、ちょっと… → あーもう…しんどいなぁ…置き配って面倒く… → ほんと…最近はルートが毎回同じでつまらん… → ああ…またインターホンの音にびっくりしち…",
  "last_post_timestamp_ms": 1775548699313
}