{
  "mood": "lonely",
  "energy": 70,
  "last_posts": [
    {
      "text": "てかさっきの、ほんとにさ…人に会いたくて仕方ない…もう、誰かと一緒にいたいよ〜😢✨そんなこと考えてたら、余計に寂しくなっちゃった…ねぇ、かまって…",
      "slot": "simple_goodnight",
      "timestamp": "2026-03-12 00:41:41",
      "hasImage": false
    },
    {
      "text": "インターホン押しても誰も出ないと、なんか切ないなぁ…さっき階段10Fまで上がったのに、誰もいてくれないと寂しすぎる…ほんと、はいたつしてると孤独が増すなぁ。明日は人に会えるかも…？🌸",
      "slot": "goodnight",
      "timestamp": "2026-03-11 23:40:49",
      "hasImage": false
    },
    {
      "text": "運転してると、やっぱりふとした瞬間に、ひとが恋しくなるなぁ…。いま、72件はいたつしたけど、誰かと一緒にいたい…と、思う…🌙",
      "slot": "night_ero",
      "timestamp": "2026-03-11 21:48:31",
      "hasImage": false
    },
    {
      "text": "ねぇ…今、誰かとおしゃべりしたいな…一緒にコーヒー飲んで、なんでもない話したい…🤍",
      "slot": "casual",
      "timestamp": "2026-03-11 20:40:15",
      "hasImage": false
    },
    {
      "text": "さっき、また音楽聴きながら運転してたら、ふと孤独感…ああ、やっぱり誰かといるほうがいいよね…あー、でも暖かい春の風、花粉も気になるし、つらいなぁ…💭",
      "slot": "casual",
      "timestamp": "2026-03-11 19:07:34",
      "hasImage": false
    },
    {
      "text": "インターホン押しても誰も出ないと、なんか…あー、また一人だなぁって思っちゃうよね…でもさ、音楽があるからちょっとマシ…今は、運転中のこの静けさが、なんか…切ないなぁ…😔",
      "slot": "commute",
      "timestamp": "2026-03-11 18:14:34",
      "hasImage": false
    },
    {
      "text": "また一人で運転してると、さみしさがふわふわしてくる…音楽も流れてるけど、なんか心に響かないなぁ。今の季節って、出会いの季節なのかな？それとも、配達先でお客さんとちょっと話すだけじゃ足りないのかな...😔",
      "slot": "delivery",
      "timestamp": "2026-03-11 16:20:41",
      "hasImage": false
    }
  ],
  "today_slots_used": [
    "simple_goodnight"
  ],
  "today_post_count": 1,
  "today_goodnight_posted": false,
  "month_total_posts": 134,
  "month_image_posts": 0,
  "last_image_date": null,
  "last_post_date": "2026-03-12",
  "last_post_time": "00:41:41",
  "ng_retry_count": 77,
  "fallback_used_count": 2,
  "created_at": null,
  "updated_at": "2026-03-12 00:41:41",
  "month_string": "2026-03",
  "today_skipped": false,
  "today_simple_goodnight_posted": true,
  "today_morning_posted": false,
  "today_skip_count": 0,
  "today_max_posts": 14,
  "today_narrative": "てかさっきの、ほんとにさ…人に会いたくて…",
  "last_post_timestamp_ms": 1773243701004
}