{
  "mood": "tired",
  "energy": 20,
  "last_posts": [
    {
      "text": "配達してると、段ボールよりも孤独が重い気がする…あーもう、しんどいなぁ。さっき子供に手振られたけど、なんか心に響かない…やっぱり誰かに会いたいよ…😞",
      "slot": "delivery",
      "timestamp": "2026-05-12 16:29:14",
      "hasImage": false
    },
    {
      "text": "さっきの続きだけど、今日も配達してきたよ！やっぱり運転しながら風を感じるのって気持ちいい～🚚✨ お客さんとのやり取りも楽しいし、今の仕事は好きだなぁ。友達も増やしたいけど、まずは仕事頑張らなきゃ！",
      "slot": "delivery",
      "timestamp": "2026-05-12 14:15:31",
      "hasImage": false
    },
    {
      "text": "さっきの続き…やっぱり、あったかくなってくると人恋しくなるね🌸 でもなんか、誰かと過ごしたいのに一人だと余計に寂しい…また桜見に行く友達見つけなきゃなぁ…😔",
      "slot": "casual",
      "timestamp": "2026-05-12 13:11:53",
      "hasImage": false
    },
    {
      "text": "なんか今日、荷物が軽くても心は重い…寂しいなぁ😩誰かと帰れたらいいのに。おっちゃんとすれ違った時に、なんか恥ずかしくなっちゃった。もうすぐ帰れるのに、なんでこんなにだるいんだろ…水分補給しよ…。",
      "slot": "commute",
      "timestamp": "2026-05-12 08:30:46",
      "hasImage": false
    },
    {
      "text": "さっきの…孤独感やばいね…むりだ、ほんと…これじゃあ桜もただの背景だし…早く誰かと話したい…😩🌸",
      "slot": "morning",
      "timestamp": "2026-05-12 07:34:27",
      "hasImage": false
    },
    {
      "text": "配達してると荷物の重さより孤独を感じてる…92件もこなしてるのに誰とも会話しないなんて😭桜が綺麗なのに見上げる余裕もない…ほんと誰かに会いたいな…",
      "slot": "delivery",
      "timestamp": "2026-05-12 01:39:27",
      "hasImage": false
    },
    {
      "text": "ほんとに、月曜のこのだるさ…エレベーターなしで運ぶのも疲れるし…最近、配達件数も147件もいったけど、なんかスッキリしない。もっと遊びたいなぁ…😔",
      "slot": "goodnight",
      "timestamp": "2026-05-11 23:12:54",
      "hasImage": false
    }
  ],
  "today_slots_used": [
    "delivery",
    "morning",
    "commute",
    "casual",
    "delivery",
    "delivery"
  ],
  "today_post_count": 6,
  "today_goodnight_posted": false,
  "month_total_posts": 139,
  "month_image_posts": 0,
  "last_image_date": null,
  "last_post_date": "2026-05-12",
  "last_post_time": "16:29:14",
  "ng_retry_count": 180,
  "fallback_used_count": 5,
  "created_at": null,
  "updated_at": "2026-05-12 16:29:14",
  "month_string": "2026-05",
  "today_skipped": false,
  "today_simple_goodnight_posted": false,
  "today_morning_posted": true,
  "today_skip_count": 0,
  "today_max_posts": 15,
  "today_narrative": "配達してると荷物の重さより孤独を感じてる… → さっきの…孤独感やばいね…むりだ、ほんと… → なんか今日、荷物が軽くても心は重い…寂し… → さっきの続き…やっぱり、あったかくなって… → さっきの続きだけど、今日も配達してきたよ… → 配達してると、段ボールよりも孤独が重い気…",
  "last_post_timestamp_ms": 1778570954156
}